random_audio/__init__.py
random_audio-1.0.1.dist-info/METADATA
random_audio-1.0.1.dist-info/RECORD
random_audio-1.0.1.dist-info/WHEEL
random_audio-1.0.1.dist-info/entry_points.txt
random_audio-1.0.1.dist-info/top_level.txt
