Metadata-Version: 2.1
Name: random-audio
Version: 1.0.1
Summary: CLI tool to generate a mash-up of audio clips
Home-page: https://github.com/jhurricane96/random_audio
Author: Arun Ramachandran
Author-email: ramachandran.arun@outlook.com
License: MIT
Platform: UNKNOWN
Classifier: Programming Language :: Python :: 3
Classifier: License :: OSI Approved :: MIT License
Classifier: Operating System :: OS Independent
Classifier: Topic :: Utilities
Requires-Dist: pydub (==0.22.0)
